multiplicationtablelib/__init__.py
multiplicationtablelib/multiplicationtable.py
multiplicationtablelib-0.1.0.dist-info/LICENSE
multiplicationtablelib-0.1.0.dist-info/METADATA
multiplicationtablelib-0.1.0.dist-info/WHEEL
multiplicationtablelib-0.1.0.dist-info/top_level.txt
multiplicationtablelib-0.1.0.dist-info/RECORD
