Metadata-Version: 2.1
Name: multiplicationtablelib
Version: 0.1.0
Summary: Python library for showing multiplication tables
Author: Sarthak, Arpit
License: MIT
License-File: LICENSE
